podman_stack-0.2.7.dist-info/licenses/LICENSE
stack/__init__.py
stack/config.py
stack/systemd.py
podman_stack-0.2.7.dist-info/METADATA
podman_stack-0.2.7.dist-info/WHEEL
podman_stack-0.2.7.dist-info/entry_points.txt
podman_stack-0.2.7.dist-info/top_level.txt
podman_stack-0.2.7.dist-info/RECORD
