Metadata-Version: 2.4
Name: podman-stack
Version: 0.2.7
Summary: Manage your podman-compose-based services.
Project-URL: Homepage, https://sr.ht/~aleksrutins/stack
Requires-Python: >=3.13
License-File: LICENSE
Requires-Dist: podman-compose>=1.4.0
Requires-Dist: typer>=0.16.0
Dynamic: license-file
